[
   {
      "idlibro":1,
      "titulo":"LA ILÍADA",
      "isbn":"978-970-07-7330-8",
      "genero":"Poesía/Ficción",
      "editorial":"PORRÚA",
      "edicion":"#38",
      "proveedor":"Librería Porrúa",
      "tipopasta":"Rústica",
      "autor":"HOMERO",
      "estado":"Bueno",
      "numpaginas":335,
      "fechaadq":"2015-03-03",
      "cantidadprest":"23"
   },
   {
      "idlibro":2,
      "titulo":"LA ODISEA",
      "isbn":"978-970-07-5827-5",
      "genero":"Poesía/Ficción",
      "editorial":"PORRÚA",
      "edicion":"#38",
      "proveedor":"Librería Porrúa",
      "tipopasta":"Rústica",
      "autor":"HOMERO",
      "estado":"Nuevo",
      "numpaginas":364,
      "fechaadq":"2015-03-03",
      "cantidadprest":"10"
   },
   {
      "idlibro":3,
      "titulo":"EL PERFUME",
      "isbn":"968-6005-17-X",
      "genero":"NOVELA/MISTERIO/TERROR/FICCIÓN HISTORICA",
      "editorial":"PLANETA MEXICANA",
      "edicion":"#50",
      "proveedor":"PLANETA MEXICANA S.A. DE C.V.",
      "tipopasta":"Rústica",
      "autor":"PATRICK SÜSKIND",
      "estado":"BUENO",
      "numpaginas":235,
      "fechaadq":"2010-10-23",
      "cantidadprest":"28"
   },
   {
      "idlibro":4,
      "titulo":"LOS HORNOS DE HITLER",
      "isbn":"968-13-1010-1",
      "genero":"NOVELA/BIOGRAFÍA/AUTOBIGRAFÍA",
      "editorial":"DIANA",
      "edicion":"#53",
      "proveedor":"EDITORIAL DIANA S.A. DE C.V.",
      "tipopasta":"Rústica",
      "autor":"OLGA LENGYEL",
      "estado":"BUENO",
      "numpaginas":263,
      "fechaadq":"2015-05-23",
      "cantidadprest":"45"
   },
   {
      "idlibro":5,
      "titulo":"REVELIÓN EN LA GRANJA",
      "isbn":"970-07-3765-9",
      "genero":"ALEGORÍA/SÁTIRA/FÁBULA/NOVELA CORTA/SÁTIRA POLITICA",
      "editorial":"PORRÚA",
      "edicion":"#5",
      "proveedor":"EDITORIAL PURRÚA S.A. DE C.V.",
      "tipopasta":"Rústica",
      "autor":"GEORGE ORWELL",
      "estado":"BUENO",
      "numpaginas":349,
      "fechaadq":"2014-08-11",
      "cantidadprest":"13"
   },
   {
      "idlibro":6,
      "titulo":"SODOMA Y GOMORRA",
      "isbn":"978-968-15-1294-1",
      "genero":"FICCIÓN",
      "editorial":"MEXICANOS UNIDOS",
      "edicion":"#8",
      "proveedor":"EDITORES MEXICANOS UNIDOS S.A. DE C.V.",
      "tipopasta":"Rústica",
      "autor":"MARCEL PROUST",
      "estado":"SEMINUEVO",
      "numpaginas":445,
      "fechaadq":"2016-12-20",
      "cantidadprest":"18"
   },
   {
      "idlibro":7,
      "titulo":"DOROTHY Y EL MAGO DE OZ",
      "isbn":"970-651-743-X",
      "genero":"FICCIÓN",
      "editorial":"MAEVA",
      "edicion":"#1",
      "proveedor":"EDITORIAL OCEANO DE MÉXICO S.A. DE C.V.",
      "tipopasta":"DURA",
      "autor":"L.FRANK BAUM",
      "estado":"SEMINUEVO",
      "numpaginas":230,
      "fechaadq":"2009-05-25",
      "cantidadprest":"20"
   },
   {
      "idlibro":8,
      "titulo":"CIEN AÑOS DE SOLEDAD",
      "isbn":"968-13-4574-X",
      "genero":"NOVELA",
      "editorial":"DIANA",
      "edicion":"#39",
      "proveedor":"EDITORIAL DIANA S.A. DE C.V.",
      "tipopasta":"RÚSTICA",
      "autor":"GABRIEL GARCÍA MÁRQUEZ",
      "estado":"BUENO",
      "numpaginas":432,
      "fechaadq":"2007-02-10",
      "cantidadprest":"56"
   },
   {
      "idlibro":9,
      "titulo":"20 MIL LEGUAS DE VIAJE SUBMARINO",
      "isbn":"970-627-270-0",
      "genero":"NOVELA/FICCIÓN/AVENTURA",
      "editorial":"EPOCA",
      "edicion":"#39",
      "proveedor":"EDITORIAL ÉPOCA S.A. DE C.V.",
      "tipopasta":"RÚSTICA",
      "autor":"JULIO VERNE",
      "estado":"NUEVO",
      "numpaginas":330,
      "fechaadq":"2018-03-25",
      "cantidadprest":"1"
   },
   {
      "idlibro":10,
      "titulo":"DON QUIJOTE DE LA MANCHA",
      "isbn":"970-627-082-5",
      "genero":"NOVELA/FICCIÓN/AVENTURA",
      "editorial":"EPOCA",
      "edicion":"#39",
      "proveedor":"EDITORIAL ÉPOCA S.A. DE C.V.",
      "tipopasta":"RÚSTICA",
      "autor":"MIGUEL DE CERVANTES SAAVEDRA",
      "estado":"BUENO",
      "numpaginas":599,
      "fechaadq":"2013-05-21",
      "cantidadprest":"33"
   },
   {
      "idlibro":11,
      "titulo":"Eragon",
      "isbn":"9788415729235",
      "genero":"Ficción",
      "editorial":"Roca Bolsillo",
      "edicion":"1",
      "proveedor":"Librería Gandhi",
      "tipopasta":"Blanda",
      "autor":"Christopher Paolini",
      "estado":"Nuevo",
      "numpaginas":656,
      "fechaadq":"2022-03-15",
      "cantidadprest":"0"
   },
   {
      "idlibro":12,
      "titulo":"Brisingr",
      "isbn":"9788417821685",
      "genero":"Ficción",
      "editorial":"Roca Bolsillo",
      "edicion":"1",
      "proveedor":"Librería Gandhi",
      "tipopasta":"Blanda",
      "autor":"Christopher Paolini",
      "estado":"Nuevo",
      "numpaginas":742,
      "fechaadq":"2022-03-15",
      "cantidadprest":"0"
   },
   {
      "idlibro":13,
      "titulo":"Eldest",
      "isbn":"9788415729242",
      "genero":"Ficción",
      "editorial":"Roca Bolsillo",
      "edicion":"1",
      "proveedor":"Librería Gandhi",
      "tipopasta":"Blanda",
      "autor":"Christopher Paolini",
      "estado":"Nuevo",
      "numpaginas":832,
      "fechaadq":"2022-03-15",
      "cantidadprest":"0"
   },
   {
      "idlibro":14,
      "titulo":"Legado",
      "isbn":"9788417821692",
      "genero":"Ficción",
      "editorial":"Roca Bolsillo",
      "edicion":"1",
      "proveedor":"Librería Gandhi",
      "tipopasta":"Blanda",
      "autor":"Christopher Paolini",
      "estado":"Nuevo",
      "numpaginas":853,
      "fechaadq":"2022-03-15",
      "cantidadprest":"0"
   },
   {
      "idlibro":15,
      "titulo":"El sobrino del mago",
      "isbn":"9789703704262",
      "genero":"Ficción",
      "editorial":"Destino México",
      "edicion":"1",
      "proveedor":"Librería Gandhi",
      "tipopasta":"Blanda",
      "autor":"C.S. Lewis",
      "estado":"Nuevo",
      "numpaginas":256,
      "fechaadq":"2022-03-15",
      "cantidadprest":"0"
   },
   {
      "idlibro":16,
      "titulo":"El león, la bruja y el armario",
      "isbn":"9789703704279",
      "genero":"Ficción",
      "editorial":"Destino México",
      "edicion":"1",
      "proveedor":"Librería Gandhi",
      "tipopasta":"Blanda",
      "autor":"C.S. Lewis",
      "estado":"Nuevo",
      "numpaginas":238,
      "fechaadq":"2022-03-15",
      "cantidadprest":"0"
   },
   {
      "idlibro":17,
      "titulo":"El caballo y el muchacho",
      "isbn":"9789703704286",
      "genero":"Ficción",
      "editorial":"Destino México",
      "edicion":"1",
      "proveedor":"Librería Gandhi",
      "tipopasta":"Blanda",
      "autor":"C.S. Lewis",
      "estado":"Nuevo",
      "numpaginas":286,
      "fechaadq":"2022-03-15",
      "cantidadprest":"0"
   },
   {
      "idlibro":18,
      "titulo":"El príncipe Caspian",
      "isbn":"9789703704293",
      "genero":"Ficción",
      "editorial":"Destino México",
      "edicion":"1",
      "proveedor":"Librería Gandhi",
      "tipopasta":"Blanda",
      "autor":"C.S. Lewis",
      "estado":"Nuevo",
      "numpaginas":288,
      "fechaadq":"2022-03-15",
      "cantidadprest":"0"
   },
   {
      "idlibro":19,
      "titulo":"La travesía del Viajero del Alba",
      "isbn":"9789703704309",
      "genero":"Ficción",
      "editorial":"Destino México",
      "edicion":"1",
      "proveedor":"Librería Gandhi",
      "tipopasta":"Blanda",
      "autor":"C.S. Lewis",
      "estado":"Nuevo",
      "numpaginas":320,
      "fechaadq":"2022-03-15",
      "cantidadprest":"0"
   },
   {
      "idlibro":20,
      "titulo":"La silla de plata",
      "isbn":"9789703704316",
      "genero":"Ficción",
      "editorial":"Destino México",
      "edicion":"1",
      "proveedor":"Librería Gandhi",
      "tipopasta":"Blanda",
      "autor":"C.S. Lewis",
      "estado":"Nuevo",
      "numpaginas":304,
      "fechaadq":"2022-03-15",
      "cantidadprest":"0"
   },
   {
      "idlibro":21,
      "titulo":"El principito",
      "isbn":"978016942",
      "genero":"Ciencia Ficcion",
      "editorial":"Campanario",
      "edicion":"oficial",
      "proveedor":"entregaLIBROS2",
      "tipopasta":"Rustica",
      "autor":"Isaac",
      "estado":"Dañado",
      "numpaginas":103,
      "fechaadq":"2004-11-01",
      "cantidadprest":"5"
   },
   {
      "idlibro":22,
      "titulo":"Momo",
      "isbn":"978013861",
      "genero":"Ciencia Ficcion",
      "editorial":"La torre",
      "edicion":"Bolsillo",
      "proveedor":"LIBROS2bonitos",
      "tipopasta":"Cartone",
      "autor":"Michel",
      "estado":"Limpio",
      "numpaginas":294,
      "fechaadq":"2003-12-10",
      "cantidadprest":"12"
   },
   {
      "idlibro":23,
      "titulo":"IT",
      "isbn":"978016710",
      "genero":"Terror",
      "editorial":"Resplandeciente",
      "edicion":"Especial",
      "proveedor":"LIBROS2Domicilio",
      "tipopasta":"Tela",
      "autor":"Auron",
      "estado":"Limpio",
      "numpaginas":323,
      "fechaadq":"2006-02-13",
      "cantidadprest":"41"
   },
   {
      "idlibro":24,
      "titulo":"Barbie",
      "isbn":"978016152",
      "genero":"Ciencia Ficcion",
      "editorial":"BuenosLIBROS2",
      "edicion":"Oficial",
      "proveedor":"IceBox",
      "tipopasta":"Rustica",
      "autor":"Katye",
      "estado":"Dañado",
      "numpaginas":98,
      "fechaadq":"2000-09-15",
      "cantidadprest":"5"
   },
   {
      "idlibro":25,
      "titulo":"Historia para primaria",
      "isbn":"978016169",
      "genero":"Educativo",
      "editorial":"Loli",
      "edicion":"Bolsillo",
      "proveedor":"TrampBook",
      "tipopasta":"Rustica",
      "autor":"Paola",
      "estado":"Dañado",
      "numpaginas":81,
      "fechaadq":"2002-04-15",
      "cantidadprest":"10"
   },
   {
      "idlibro":26,
      "titulo":"GotnoTime",
      "isbn":"78016990",
      "genero":"Suspenso",
      "editorial":"Campanario",
      "edicion":"Oficial",
      "proveedor":"EntregaRapida",
      "tipopasta":"Holandesa",
      "autor":"LivingStone",
      "estado":"Limpio",
      "numpaginas":501,
      "fechaadq":"2016-09-12",
      "cantidadprest":"1"
   },
   {
      "idlibro":27,
      "titulo":"Winnie Pooh",
      "isbn":"78016191",
      "genero":"Ciencia ficcion",
      "editorial":"La torre",
      "edicion":"Ilustrada",
      "proveedor":"Rapidin",
      "tipopasta":"Cartone",
      "autor":"Richard",
      "estado":"Dañado",
      "numpaginas":101,
      "fechaadq":"2015-01-02",
      "cantidadprest":"0"
   },
   {
      "idlibro":28,
      "titulo":"Gramatica basica",
      "isbn":"78016400",
      "genero":"Educativo",
      "editorial":"Los z",
      "edicion":"de lujo",
      "proveedor":"VelocidadLuz",
      "tipopasta":"Rustica",
      "autor":"Laura",
      "estado":"Limpio",
      "numpaginas":50,
      "fechaadq":"2019-06-15",
      "cantidadprest":"12"
   },
   {
      "idlibro":29,
      "titulo":"El sistema solar",
      "isbn":"78016991",
      "genero":"Eduativo",
      "editorial":"GoodBook",
      "edicion":"de lujo",
      "proveedor":"FeelGood",
      "tipopasta":"Tela",
      "autor":"Andres",
      "estado":"Limpio",
      "numpaginas":29,
      "fechaadq":"2019-09-05",
      "cantidadprest":"33"
   },
   {
      "idlibro":30,
      "titulo":"Sister location",
      "isbn":"78016922",
      "genero":"Terror",
      "editorial":"BuenosLIBROS2",
      "edicion":"especial",
      "proveedor":"TwoTimes",
      "tipopasta":"Tela",
      "autor":"Scott",
      "estado":"Limpio",
      "numpaginas":37,
      "fechaadq":"2018-06-12",
      "cantidadprest":"11"
   },
   {
      "idlibro":31,
      "titulo":"Mistborn",
      "isbn":"32-32-32",
      "genero":"Ficción",
      "editorial":"PORRÚA",
      "edicion":"8",
      "proveedor":"Librería Nose",
      "tipopasta":"Rústica",
      "autor":"MAQUIAVELO",
      "estado":"MALO",
      "numpaginas":325,
      "fechaadq":"2019-09-03",
      "cantidadprest":"23"
   },
   {
      "idlibro":32,
      "titulo":"Libro nose",
      "isbn":"325-63-32",
      "genero":"Poesía",
      "editorial":"PORRÚA",
      "edicion":"98",
      "proveedor":"Librería Nose",
      "tipopasta":"Rústica",
      "autor":"HOMERO",
      "estado":"Nuevo",
      "numpaginas":354,
      "fechaadq":"2015-02-09",
      "cantidadprest":"19"
   },
   {
      "idlibro":33,
      "titulo":"Skyward",
      "isbn":"2332-54-5",
      "genero":"HISTORICA",
      "editorial":"MEXICANA EDIT",
      "edicion":"50",
      "proveedor":"MEXICO SA",
      "tipopasta":"Rústica",
      "autor":"MAQUIAVELO",
      "estado":"BUENO",
      "numpaginas":135,
      "fechaadq":"2010-01-23",
      "cantidadprest":"28"
   },
   {
      "idlibro":34,
      "titulo":"Cytonic",
      "isbn":"23-4-5-56",
      "genero":"Fantasia",
      "editorial":"DIANA",
      "edicion":"3",
      "proveedor":"EDITORIAL ANTOHN",
      "tipopasta":"Rústica",
      "autor":"OLGA LENGYEL",
      "estado":"BUENO",
      "numpaginas":243,
      "fechaadq":"2011-05-23",
      "cantidadprest":"45"
   },
   {
      "idlibro":35,
      "titulo":"The way of kings",
      "isbn":"64-24-31-1",
      "genero":"HISTORICA",
      "editorial":"PORRÚA",
      "edicion":"5",
      "proveedor":"EDITORIAL URA",
      "tipopasta":"Rústica",
      "autor":"GEORGE LEBLOS",
      "estado":"MALO",
      "numpaginas":149,
      "fechaadq":"2011-08-11",
      "cantidadprest":"13"
   },
   {
      "idlibro":36,
      "titulo":"Hunger games",
      "isbn":"21-3-45",
      "genero":"HISTORICA",
      "editorial":"MEXICANOS UNIDOS",
      "edicion":"8",
      "proveedor":"EDITORES UNIDOS S.A. DE C.V.",
      "tipopasta":"Rústica",
      "autor":"Brandon Sanderson",
      "estado":"SEMINUEVO",
      "numpaginas":445,
      "fechaadq":"2011-12-20",
      "cantidadprest":"18"
   },
   {
      "idlibro":37,
      "titulo":"Nose 2",
      "isbn":"324-5-6-6",
      "genero":"FICCIÓN",
      "editorial":"MAEVA",
      "edicion":"1",
      "proveedor":"EDITORIAL OCEANO DE MÉXICO S.A. DE C.V.",
      "tipopasta":"DURA",
      "autor":"Brandon Sanderson",
      "estado":"SEMINUEVO",
      "numpaginas":530,
      "fechaadq":"2009-01-20",
      "cantidadprest":"20"
   },
   {
      "idlibro":38,
      "titulo":"Nose 3",
      "isbn":"1-23-34-4",
      "genero":"CIENCIA",
      "editorial":"DIANA P. E.",
      "edicion":"3",
      "proveedor":"EDITORIAL PERRO",
      "tipopasta":"RÚSTICA",
      "autor":"Brandon Sanderson",
      "estado":"BUENO",
      "numpaginas":433,
      "fechaadq":"2017-02-10",
      "cantidadprest":"56"
   },
   {
      "idlibro":39,
      "titulo":"The final Empire",
      "isbn":"5645-34-2-2",
      "genero":"CIENCIA",
      "editorial":"EPOCA",
      "edicion":"9",
      "proveedor":"EDITORIAL TREN",
      "tipopasta":"RÚSTICA",
      "autor":"Brandon Sanderson",
      "estado":"NUEVO",
      "numpaginas":830,
      "fechaadq":"2022-03-25",
      "cantidadprest":"1"
   },
   {
      "idlibro":40,
      "titulo":"Mistborn 5",
      "isbn":"3212-31-3",
      "genero":"FANTASIA",
      "editorial":"EPOCA",
      "edicion":"3",
      "proveedor":"EDITORIAL ÉPOCA S.A. DE C.V.",
      "tipopasta":"RÚSTICA",
      "autor":"Brandon Sanderson",
      "estado":"BUENO",
      "numpaginas":199,
      "fechaadq":"2018-05-21",
      "cantidadprest":"33"
   },
   {
      "idlibro":41,
      "titulo":"Arreglos lineales",
      "isbn":"185634",
      "genero":"ACADEMICO",
      "editorial":"aldama",
      "edicion":"1ERA",
      "proveedor":"PORRUA",
      "tipopasta":"TAPA DURA",
      "autor":"CARLOS ALDAMA",
      "estado":"PRESTADO",
      "numpaginas":280,
      "fechaadq":"2012-12-22",
      "cantidadprest":"100"
   },
   {
      "idlibro":42,
      "titulo":"Procesadores de audio",
      "isbn":"185635",
      "genero":"ACADEMICO",
      "editorial":"aldama",
      "edicion":"2DA",
      "proveedor":"PORRUA",
      "tipopasta":"TAPA DURA",
      "autor":"CARLOS ALDAMA",
      "estado":"PRESTADO",
      "numpaginas":320,
      "fechaadq":"2010-12-22",
      "cantidadprest":"25"
   },
   {
      "idlibro":43,
      "titulo":"La física del audio",
      "isbn":"185636",
      "genero":"ACADEMICO",
      "editorial":"aldama",
      "edicion":"3ERA",
      "proveedor":"PORRUA",
      "tipopasta":"TAPA DURA",
      "autor":"CARLOS ALDAMA",
      "estado":"PRESTADO",
      "numpaginas":400,
      "fechaadq":"2007-12-22",
      "cantidadprest":"75"
   },
   {
      "idlibro":44,
      "titulo":"Diseño de arreglos linales",
      "isbn":"185637",
      "genero":"ACADEMICO",
      "editorial":"aldama",
      "edicion":"5TA",
      "proveedor":"PORRUA",
      "tipopasta":"TAPA DURA",
      "autor":"CARLOS ALDAMA",
      "estado":"PRESTADO",
      "numpaginas":190,
      "fechaadq":"2008-12-22",
      "cantidadprest":"200"
   },
   {
      "idlibro":45,
      "titulo":"C++ desde 0",
      "isbn":"185638",
      "genero":"ACADEMICO",
      "editorial":"edteam",
      "edicion":"1RA",
      "proveedor":"aldama",
      "tipopasta":"TAPA DURA",
      "autor":"JOSH GONZALEZ",
      "estado":"PRESTADO",
      "numpaginas":500,
      "fechaadq":"2012-12-22",
      "cantidadprest":"100"
   },
   {
      "idlibro":46,
      "titulo":"Algoritmos",
      "isbn":"185639",
      "genero":"ACADEMICO",
      "editorial":"edteam",
      "edicion":"6TA",
      "proveedor":"edteam.store",
      "tipopasta":"TAPA DURA",
      "autor":"ALVARO FELIPE",
      "estado":"PRESTADO",
      "numpaginas":400,
      "fechaadq":"2016-12-22",
      "cantidadprest":"150"
   },
   {
      "idlibro":47,
      "titulo":"Python",
      "isbn":"185640",
      "genero":"ACADEMICO",
      "editorial":"edteam",
      "edicion":"7MA",
      "proveedor":"edteam.store",
      "tipopasta":"TAPA DURA",
      "autor":"ALEXIS LOZADA",
      "estado":"PRESTADO",
      "numpaginas":200,
      "fechaadq":"2016-12-22",
      "cantidadprest":"80"
   },
   {
      "idlibro":48,
      "titulo":"Atomic Design",
      "isbn":"185641",
      "genero":"ACADEMICO",
      "editorial":"edteam",
      "edicion":"1ERA",
      "proveedor":"edteam.store",
      "tipopasta":"TAPA DURA",
      "autor":"ALVARO FELIPE",
      "estado":"PRESTADO",
      "numpaginas":200,
      "fechaadq":"2020-12-22",
      "cantidadprest":"40"
   },
   {
      "idlibro":49,
      "titulo":"AWS desde 0",
      "isbn":"185642",
      "genero":"ACADEMICO",
      "editorial":"edteam",
      "edicion":"1ERA",
      "proveedor":"edteam.store",
      "tipopasta":"TAPA DURA",
      "autor":"BETO QUIROGA",
      "estado":"PRESTADO",
      "numpaginas":300,
      "fechaadq":"2018-12-22",
      "cantidadprest":"50"
   },
   {
      "idlibro":50,
      "titulo":"Golang desde 0",
      "isbn":"185643",
      "genero":"ACADEMICO",
      "editorial":"edteam",
      "edicion":"1ERA",
      "proveedor":"edteam.store",
      "tipopasta":"TAPA DURA",
      "autor":"ALVARO FELIPE",
      "estado":"PRESTADO",
      "numpaginas":100,
      "fechaadq":"2016-12-22",
      "cantidadprest":"10"
   },
   {
      "idlibro":51,
      "titulo":"Harry Potter",
      "isbn":"9780439362139",
      "genero":"Ficción Fantastica",
      "editorial":"Salamandra",
      "edicion":"1",
      "proveedor":"Abastecedora Lumen",
      "tipopasta":"Tapa blanda",
      "autor":"J. K. Rowling",
      "estado":"Inactivo",
      "numpaginas":244,
      "fechaadq":"2017-05-16",
      "cantidadprest":"115"
   },
   {
      "idlibro":52,
      "titulo":"El Señor de los Anillos",
      "isbn":"9780007203581",
      "genero":"Ficción Fantastica",
      "editorial":"Booket",
      "edicion":"1",
      "proveedor":"Abastecedora Lumen",
      "tipopasta":"Tapa blanda",
      "autor":"J. R. R. Tolkien",
      "estado":"Inactivo",
      "numpaginas":184,
      "fechaadq":"2017-05-16",
      "cantidadprest":"96"
   },
   {
      "idlibro":53,
      "titulo":"El Alquimista",
      "isbn":"9781867203521",
      "genero":"Drama",
      "editorial":"Grijalbo",
      "edicion":"1",
      "proveedor":"Abastecedora Lumen",
      "tipopasta":"Tapa blanda",
      "autor":"Paulo Coelho",
      "estado":"Activo",
      "numpaginas":266,
      "fechaadq":"2017-05-16",
      "cantidadprest":"115"
   },
   {
      "idlibro":54,
      "titulo":"El Código da Vinci",
      "isbn":"9782717476612",
      "genero":"Ficción Conspirativa",
      "editorial":"Planeta",
      "edicion":"1",
      "proveedor":"Abastecedora Lumen",
      "tipopasta":"Tapa blanda",
      "autor":"Dan Brown",
      "estado":"Inactivo",
      "numpaginas":156,
      "fechaadq":"2017-05-16",
      "cantidadprest":"85"
   },
   {
      "idlibro":55,
      "titulo":"Crepúsculo",
      "isbn":"9781468716138",
      "genero":"Ficción Fantastica",
      "editorial":"Debolsillo",
      "edicion":"1",
      "proveedor":"Abastecedora Lumen",
      "tipopasta":"Tapa blanda",
      "autor":"Stephenie Meyer",
      "estado":"Activo",
      "numpaginas":194,
      "fechaadq":"2017-05-16",
      "cantidadprest":"120"
   },
   {
      "idlibro":56,
      "titulo":"Lo que el viento se llevó",
      "isbn":"9781846171549",
      "genero":"Ficción Historica",
      "editorial":"Maxi",
      "edicion":"1",
      "proveedor":"Abastecedora Lumen",
      "tipopasta":"Tapa blanda",
      "autor":"Margaret Mitchell",
      "estado":"Inactivo",
      "numpaginas":205,
      "fechaadq":"2017-05-16",
      "cantidadprest":"81"
   },
   {
      "idlibro":57,
      "titulo":"Piense y hágase rico",
      "isbn":"9785642167432",
      "genero":"Autoayuda",
      "editorial":"Grijalbo",
      "edicion":"1",
      "proveedor":"Abastecedora Lumen",
      "tipopasta":"Tapa blanda",
      "autor":"Napoleon Hill",
      "estado":"Activo",
      "numpaginas":176,
      "fechaadq":"2017-05-16",
      "cantidadprest":"74"
   },
   {
      "idlibro":58,
      "titulo":"El diario de Ana Frank",
      "isbn":"9784568048744",
      "genero":"Autobiografía",
      "editorial":"Debolsillo",
      "edicion":"1",
      "proveedor":"Abastecedora Lumen",
      "tipopasta":"Tapa blanda",
      "autor":"Ana Frank",
      "estado":"Activo",
      "numpaginas":144,
      "fechaadq":"2017-05-16",
      "cantidadprest":"129"
   },
   {
      "idlibro":59,
      "titulo":"El extranjero",
      "isbn":"9781867767154",
      "genero":"Ficción Fantastica",
      "editorial":"AlgaR",
      "edicion":"1",
      "proveedor":"Abastecedora Lumen",
      "tipopasta":"Tapa blanda",
      "autor":"Albert Camus",
      "estado":"Inactivo",
      "numpaginas":185,
      "fechaadq":"2017-09-16",
      "cantidadprest":"116"
   },
   {
      "idlibro":60,
      "titulo":"Don Quijote de la Mancha",
      "isbn":"9780744536256",
      "genero":"Ficción Fantastica",
      "editorial":"AlgaR",
      "edicion":"1",
      "proveedor":"Abastecedora Lumen",
      "tipopasta":"Tapa blanda",
      "autor":"Miguel de Cervantes",
      "estado":"Inactivo",
      "numpaginas":236,
      "fechaadq":"2017-05-16",
      "cantidadprest":"83"
   },
   {
      "idlibro":61,
      "titulo":"Nada",
      "isbn":"9780151666201",
      "genero":"ficcion",
      "editorial":"Heder México",
      "edicion":"#61",
      "proveedor":"Heder",
      "tipopasta":"tapadura",
      "autor":"Carmen Laforet",
      "estado":"Nuevo",
      "numpaginas":326,
      "fechaadq":"2021-09-22",
      "cantidadprest":""
   },
   {
      "idlibro":62,
      "titulo":"Los Miserables",
      "isbn":"9780121660346",
      "genero":"ficcion",
      "editorial":"Heder México",
      "edicion":"#62",
      "proveedor":"Heder",
      "tipopasta":"tapadura",
      "autor":"Víctor Hugo",
      "estado":"Nuevo",
      "numpaginas":322,
      "fechaadq":"2021-09-23",
      "cantidadprest":"02"
   },
   {
      "idlibro":63,
      "titulo":"El Alquimista",
      "isbn":"9780111660346",
      "genero":"ficcion",
      "editorial":"Heder México",
      "edicion":"#63",
      "proveedor":"Heder",
      "tipopasta":"tapadura",
      "autor":"Paulo Coelho",
      "estado":"Nuevo",
      "numpaginas":276,
      "fechaadq":"2021-09-24",
      "cantidadprest":"5"
   },
   {
      "idlibro":64,
      "titulo":"La Divina Comedia",
      "isbn":"9740551680346",
      "genero":"ficcion",
      "editorial":"Heder México",
      "edicion":"#64",
      "proveedor":"Heder",
      "tipopasta":"tapadura",
      "autor":"Dante",
      "estado":"Nuevo",
      "numpaginas":311,
      "fechaadq":"2021-09-25",
      "cantidadprest":"8"
   },
   {
      "idlibro":65,
      "titulo":"Cien años de Soledad",
      "isbn":"9380151660746",
      "genero":"ficcion",
      "editorial":"Heder México",
      "edicion":"#65",
      "proveedor":"Heder",
      "tipopasta":"tapadura",
      "autor":"Gabriel García Márquez",
      "estado":"Nuevo",
      "numpaginas":153,
      "fechaadq":"2021-09-26",
      "cantidadprest":"9"
   },
   {
      "idlibro":66,
      "titulo":"El Principito",
      "isbn":"9780151920546",
      "genero":"ficcion",
      "editorial":"Heder México",
      "edicion":"#66",
      "proveedor":"Heder",
      "tipopasta":"tapadura",
      "autor":"Antoine de Saint-Exupéry",
      "estado":"Nuevo",
      "numpaginas":326,
      "fechaadq":"2021-09-27",
      "cantidadprest":"10"
   },
   {
      "idlibro":67,
      "titulo":"Un mundo feliz",
      "isbn":"9780151660346",
      "genero":"ficcion",
      "editorial":"Heder México",
      "edicion":"#67",
      "proveedor":"Heder",
      "tipopasta":"tapadura",
      "autor":"Oscar Wilde",
      "estado":"Nuevo",
      "numpaginas":126,
      "fechaadq":"2021-09-28",
      "cantidadprest":"12"
   },
   {
      "idlibro":68,
      "titulo":"El asesino",
      "isbn":"9780151080111",
      "genero":"ficcion",
      "editorial":"Heder México",
      "edicion":"#68",
      "proveedor":"Heder",
      "tipopasta":"tapadura",
      "autor":"Aldous Huxley",
      "estado":"Nuevo",
      "numpaginas":323,
      "fechaadq":"2021-09-29",
      "cantidadprest":"12"
   },
   {
      "idlibro":69,
      "titulo":"Cartas amor muertos",
      "isbn":"9780151089146",
      "genero":"ficcion",
      "editorial":"Heder México",
      "edicion":"#69",
      "proveedor":"Heder",
      "tipopasta":"tapadura",
      "autor":"Aldous Huxley",
      "estado":"Nuevo",
      "numpaginas":323,
      "fechaadq":"2021-04-29",
      "cantidadprest":"12"
   },
   {
      "idlibro":70,
      "titulo":"Antes de diciembre",
      "isbn":"9780151081236",
      "genero":"ficcion",
      "editorial":"Heder México",
      "edicion":"#70",
      "proveedor":"Heder",
      "tipopasta":"tapadura",
      "autor":"Aldous Huxley",
      "estado":"Nuevo",
      "numpaginas":323,
      "fechaadq":"2021-09-29",
      "cantidadprest":"12"
   },
   {
      "idlibro":81,
      "titulo":"Cerdo capitalista",
      "isbn":"123libro",
      "genero":"Economia",
      "editorial":"Aguilar",
      "edicion":"edicion_001",
      "proveedor":"libritos",
      "tipopasta":"Rústica",
      "autor":"Sofia Macias",
      "estado":"libre",
      "numpaginas":253,
      "fechaadq":"2012-05-09",
      "cantidadprest":"56"
   },
   {
      "idlibro":82,
      "titulo":"los 7 habitos de la gente altamente efectiva",
      "isbn":"124libro",
      "genero":"psicologia",
      "editorial":"Aguilar",
      "edicion":"edicion_001",
      "proveedor":"libritos",
      "tipopasta":"Rústica",
      "autor":"Sofia Macias",
      "estado":"libre",
      "numpaginas":253,
      "fechaadq":"2012-05-09",
      "cantidadprest":"56"
   },
   {
      "idlibro":83,
      "titulo":"programacion a fondo ",
      "isbn":"1235libro",
      "genero":"Programacion",
      "editorial":"Aguilar",
      "edicion":"edicion_001",
      "proveedor":"libritos",
      "tipopasta":"Rústica",
      "autor":"pablo Agusto",
      "estado":"libre",
      "numpaginas":253,
      "fechaadq":"2012-05-09",
      "cantidadprest":"19"
   },
   {
      "idlibro":84,
      "titulo":"si si es con tigo ",
      "isbn":"126libro",
      "genero":"Romance",
      "editorial":"Aguilar",
      "edicion":"edicion_001",
      "proveedor":"libritos",
      "tipopasta":"Rústica",
      "autor":"mariajose y daniela",
      "estado":"libre",
      "numpaginas":253,
      "fechaadq":"2012-05-09",
      "cantidadprest":"5"
   },
   {
      "idlibro":85,
      "titulo":"principito",
      "isbn":"127libro",
      "genero":"ilucion",
      "editorial":"Aguilar",
      "edicion":"edicion_001",
      "proveedor":"libritos",
      "tipopasta":"Rústica",
      "autor":"Antoine de Saint-Exupéry",
      "estado":"libre",
      "numpaginas":253,
      "fechaadq":"2012-05-09",
      "cantidadprest":"15"
   },
   {
      "idlibro":86,
      "titulo":"Romeo y Julieta",
      "isbn":"128libro",
      "genero":"Romance",
      "editorial":"Aguilar",
      "edicion":"edicion_001",
      "proveedor":"libritos",
      "tipopasta":"Rústica",
      "autor":"William Shakespeare",
      "estado":"libre",
      "numpaginas":253,
      "fechaadq":"2012-05-09",
      "cantidadprest":"17"
   },
   {
      "idlibro":87,
      "titulo":"Harry Potter",
      "isbn":"129libro",
      "genero":"Ciencia ficion ",
      "editorial":"Aguilar",
      "edicion":"edicion_001",
      "proveedor":"libritos",
      "tipopasta":"Rústica",
      "autor":"J.K. Rowling",
      "estado":"ocupado",
      "numpaginas":253,
      "fechaadq":"2012-05-09",
      "cantidadprest":"20"
   },
   {
      "idlibro":88,
      "titulo":"El Señor de los Anillos",
      "isbn":"121libro",
      "genero":"Ciencia ficion",
      "editorial":"Aguilar",
      "edicion":"edicion_001",
      "proveedor":"libritos",
      "tipopasta":"Rústica",
      "autor":"J.R.R. Tolkien",
      "estado":"libre",
      "numpaginas":253,
      "fechaadq":"2012-05-09",
      "cantidadprest":"20"
   },
   {
      "idlibro":89,
      "titulo":"Crepúsculo – La saga",
      "isbn":"122libro",
      "genero":"Romance",
      "editorial":"Aguilar",
      "edicion":"edicion_001",
      "proveedor":"libritos",
      "tipopasta":"Rústica",
      "autor":"Stephenie Meyer",
      "estado":"libre",
      "numpaginas":253,
      "fechaadq":"2012-05-09",
      "cantidadprest":"95"
   },
   {
      "idlibro":90,
      "titulo":"Lo que el viento se llevó",
      "isbn":"1210libro",
      "genero":"Ciencia ficion",
      "editorial":"Aguilar",
      "edicion":"edicion_001",
      "proveedor":"libritos",
      "tipopasta":"Rústica",
      "autor":"Margaret Mitchell",
      "estado":"libre",
      "numpaginas":253,
      "fechaadq":"2012-05-09",
      "cantidadprest":"10"
   },
   {
      "idlibro":91,
      "titulo":"MATEMATICAS",
      "isbn":"132132",
      "genero":"ACADEMICO",
      "editorial":"PORRUA",
      "edicion":"1ERA",
      "proveedor":"PORRUA",
      "tipopasta":"TAPA DURA",
      "autor":"JAVIER MARQUEZ",
      "estado":"NUEVO",
      "numpaginas":200,
      "fechaadq":"2005-12-22",
      "cantidadprest":"100"
   },
   {
      "idlibro":92,
      "titulo":"ESPAÑOL",
      "isbn":"132133",
      "genero":"ACADEMICO",
      "editorial":"PORRUA",
      "edicion":"2DA",
      "proveedor":"PORRUA",
      "tipopasta":"TAPA DURA",
      "autor":"LEONARDO RODRIGUEZ",
      "estado":"NUEVO",
      "numpaginas":300,
      "fechaadq":"2005-12-22",
      "cantidadprest":"25"
   },
   {
      "idlibro":93,
      "titulo":"QUIMICA",
      "isbn":"132134",
      "genero":"ACADEMICO",
      "editorial":"PORRUA",
      "edicion":"3ERA",
      "proveedor":"PORRUA",
      "tipopasta":"TAPA DURA",
      "autor":"ALEJANDRO LOPEZ",
      "estado":"NUEVO",
      "numpaginas":250,
      "fechaadq":"2005-12-22",
      "cantidadprest":"75"
   },
   {
      "idlibro":94,
      "titulo":"ALGEBRA",
      "isbn":"132135",
      "genero":"ACADEMICO",
      "editorial":"PORRUA",
      "edicion":"4TA",
      "proveedor":"PORRUA",
      "tipopasta":"TAPA DURA",
      "autor":"YESSENIA GUZMAN",
      "estado":"NUEVO",
      "numpaginas":150,
      "fechaadq":"2005-12-22",
      "cantidadprest":"200"
   },
   {
      "idlibro":95,
      "titulo":"FISICA",
      "isbn":"132136",
      "genero":"ACADEMICO",
      "editorial":"PORRUA",
      "edicion":"5TA",
      "proveedor":"PORRUA",
      "tipopasta":"TAPA DURA",
      "autor":"JOAN AGUILAR",
      "estado":"NUEVO",
      "numpaginas":500,
      "fechaadq":"2005-12-22",
      "cantidadprest":"100"
   },
   {
      "idlibro":96,
      "titulo":"PROGRAMACION",
      "isbn":"132137",
      "genero":"ACADEMICO",
      "editorial":"PORRUA",
      "edicion":"6TA",
      "proveedor":"PORRUA",
      "tipopasta":"TAPA DURA",
      "autor":"JOSE PERALES",
      "estado":"SEMINUEVO",
      "numpaginas":400,
      "fechaadq":"2005-12-22",
      "cantidadprest":"150"
   },
   {
      "idlibro":97,
      "titulo":"ALGEBRA LINEAL",
      "isbn":"132138",
      "genero":"ACADEMICO",
      "editorial":"PORRUA",
      "edicion":"7MA",
      "proveedor":"PORRUA",
      "tipopasta":"TAPA DURA",
      "autor":"MARCO SUAREZ",
      "estado":"SEMINUEVO",
      "numpaginas":200,
      "fechaadq":"2005-12-22",
      "cantidadprest":"80"
   },
   {
      "idlibro":98,
      "titulo":"MATEMATICAS COMPUTACIONALES",
      "isbn":"132139",
      "genero":"ACADEMICO",
      "editorial":"PORRUA",
      "edicion":"8VA",
      "proveedor":"PORRUA",
      "tipopasta":"TAPA DURA",
      "autor":"ALAN CABRERA",
      "estado":"SEMINUEVO",
      "numpaginas":200,
      "fechaadq":"2005-12-22",
      "cantidadprest":"40"
   },
   {
      "idlibro":99,
      "titulo":"INGLÉS",
      "isbn":"132140",
      "genero":"ACADEMICO",
      "editorial":"PORRUA",
      "edicion":"9NA",
      "proveedor":"PORRUA",
      "tipopasta":"TAPA DURA",
      "autor":"ZAIRA MONTOYA",
      "estado":"SEMINUEVO",
      "numpaginas":300,
      "fechaadq":"2005-12-22",
      "cantidadprest":"50"
   },
   {
      "idlibro":100,
      "titulo":"REDES",
      "isbn":"132141",
      "genero":"ACADEMICO",
      "editorial":"PORRUA",
      "edicion":"10MA",
      "proveedor":"PORRUA",
      "tipopasta":"TAPA DURA",
      "autor":"NAYMA MENDOZA",
      "estado":"SEMINUEVO",
      "numpaginas":100,
      "fechaadq":"2005-12-22",
      "cantidadprest":"10"
   },
   {
      "idlibro":101,
      "titulo":"pie grande",
      "isbn":"673-373-337-37-",
      "genero":"Ficción",
      "editorial":"viadas",
      "edicion":"#1",
      "proveedor":"LIBROS2 bonitos",
      "tipopasta":"dura",
      "autor":"HOMERO",
      "estado":"Bueno",
      "numpaginas":33,
      "fechaadq":"2022-02-01",
      "cantidadprest":"73"
   },
   {
      "idlibro":102,
      "titulo":"pie grande 2",
      "isbn":"76381-257-2768",
      "genero":"Ficción",
      "editorial":"viadas",
      "edicion":"#1",
      "proveedor":"LIBROS2 bonitos",
      "tipopasta":"dura",
      "autor":"HOMERO",
      "estado":"Nuevo",
      "numpaginas":569,
      "fechaadq":"2022-02-01",
      "cantidadprest":"0"
   },
   {
      "idlibro":103,
      "titulo":"pie pequeño",
      "isbn":"6378-55786-1758",
      "genero":"Ficción",
      "editorial":"viadas",
      "edicion":"#1",
      "proveedor":"LIBROS2 bonitos",
      "tipopasta":"dura",
      "autor":"juyan",
      "estado":"BUENO",
      "numpaginas":999,
      "fechaadq":"2022-02-01",
      "cantidadprest":"2"
   },
   {
      "idlibro":104,
      "titulo":"los panas",
      "isbn":"61827-526832-781682",
      "genero":"Fábula",
      "editorial":"viadas",
      "edicion":"#1",
      "proveedor":"LIBROS2 bonitos",
      "tipopasta":"dura",
      "autor":"olga",
      "estado":"BUENO",
      "numpaginas":12,
      "fechaadq":"2022-02-01",
      "cantidadprest":"5"
   },
   {
      "idlibro":105,
      "titulo":"los capos",
      "isbn":"75-45-7826",
      "genero":"Ficción",
      "editorial":"PORRÚA",
      "edicion":"#1",
      "proveedor":"LIBROS2 bonitos",
      "tipopasta":"Rústica",
      "autor":"alma marcela",
      "estado":"Nuevo",
      "numpaginas":67,
      "fechaadq":"2022-02-01",
      "cantidadprest":"8"
   },
   {
      "idlibro":106,
      "titulo":"los mas capos",
      "isbn":"67328-768-6579",
      "genero":"Ficción",
      "editorial":"elcometa",
      "edicion":"#1",
      "proveedor":"el libretón",
      "tipopasta":"Rústica",
      "autor":"marcelo",
      "estado":"Nuevo",
      "numpaginas":167,
      "fechaadq":"2022-02-01",
      "cantidadprest":"6"
   },
   {
      "idlibro":107,
      "titulo":"los mas capitos",
      "isbn":"931-67381-72681",
      "genero":"Ficción",
      "editorial":"elcometa",
      "edicion":"#1",
      "proveedor":"el libretón",
      "tipopasta":"delgada",
      "autor":"garcia márquez",
      "estado":"SEMINUEVO",
      "numpaginas":230,
      "fechaadq":"2022-02-01",
      "cantidadprest":"2"
   },
   {
      "idlibro":108,
      "titulo":"los mas capos 2",
      "isbn":"527-183926-540",
      "genero":"NOVELA",
      "editorial":"elcometa",
      "edicion":"#2",
      "proveedor":"el libretón",
      "tipopasta":"delgada",
      "autor":"grabiel",
      "estado":"Nuevo",
      "numpaginas":432,
      "fechaadq":"2022-02-01",
      "cantidadprest":"6"
   },
   {
      "idlibro":109,
      "titulo":"el principito",
      "isbn":"172-63817-16782",
      "genero":"Ficción",
      "editorial":"elcometa",
      "edicion":"#3",
      "proveedor":"la libreria pro",
      "tipopasta":"dura",
      "autor":"julio",
      "estado":"Nuevo",
      "numpaginas":801,
      "fechaadq":"2022-02-01",
      "cantidadprest":"2"
   },
   {
      "idlibro":110,
      "titulo":"el chueco",
      "isbn":"16782-42768-2476",
      "genero":"Aventura",
      "editorial":"planeta",
      "edicion":"#2",
      "proveedor":"la libreria pro",
      "tipopasta":"delgada",
      "autor":"Obed",
      "estado":"bueno",
      "numpaginas":579,
      "fechaadq":"2022-02-01",
      "cantidadprest":"1"
   },
   {
      "idlibro":111,
      "titulo":"PENSANDOLO BIEN PENSE MAL",
      "isbn":"9796855734078",
      "genero":"BIOGRAFÍA",
      "editorial":"CASTELLANOS EDITORES",
      "edicion":"#02",
      "proveedor":"LIBRERIAS GANDHI",
      "tipopasta":"RUSTICO",
      "autor":"JOSE MADERO",
      "estado":"BUENO",
      "numpaginas":335,
      "fechaadq":"2014-04-05",
      "cantidadprest":"08"
   },
   {
      "idlibro":112,
      "titulo":"EL INSTITUTO",
      "isbn":"9786073184335",
      "genero":"Terror/Ficción",
      "editorial":"PLAZA JANÉS",
      "edicion":"#01",
      "proveedor":"LIBRERIAS GANDHI",
      "tipopasta":"RUSTICO",
      "autor":"STEPHEN KING",
      "estado":"NUEVO",
      "numpaginas":624,
      "fechaadq":"2019-05-04",
      "cantidadprest":"01"
   },
   {
      "idlibro":113,
      "titulo":"DRACULA",
      "isbn":"9788491053484",
      "genero":"Terror/Ficción",
      "editorial":"PENGUIN CLASICOS",
      "edicion":"#10",
      "proveedor":"LIBRERIAS GANDHI",
      "tipopasta":"RUSTICO",
      "autor":"BRAM STOKER",
      "estado":"BUENO",
      "numpaginas":504,
      "fechaadq":"2021-12-10",
      "cantidadprest":"30"
   },
   {
      "idlibro":114,
      "titulo":"CEMENTERIO DE ANIMALES",
      "isbn":"9786073179324",
      "genero":"Terror/Ficción",
      "editorial":"DEBOLSILLO",
      "edicion":"#02",
      "proveedor":"LIBRERIAS GANDHI",
      "tipopasta":"DE BOLSILLO/TAPA BLANDA",
      "autor":"STEPHEN KING",
      "estado":"BUENO",
      "numpaginas":488,
      "fechaadq":"2019-05-10",
      "cantidadprest":"15"
   },
   {
      "idlibro":115,
      "titulo":"IT",
      "isbn":"9788497593793",
      "genero":"Novela/Terror/Ficción",
      "editorial":"DEBOLSILLO",
      "edicion":"#02",
      "proveedor":"CASA DEL LIBRO",
      "tipopasta":"RUSTICO",
      "autor":"STEPHEN KING",
      "estado":"BUENO",
      "numpaginas":1504,
      "fechaadq":"2016-07-09",
      "cantidadprest":"13"
   },
   {
      "idlibro":117,
      "titulo":"1984",
      "isbn":"9788412270518",
      "genero":"Ficción",
      "editorial":"LIBROS2 DEL ZORRO ROJO",
      "edicion":"#05",
      "proveedor":"LIBRERIAS GANDHI",
      "tipopasta":"BOLSILLO/TAPA BLANDA",
      "autor":"GEORGE ORWELL",
      "estado":"NUEVO",
      "numpaginas":360,
      "fechaadq":"2021-03-03",
      "cantidadprest":"02"
   },
   {
      "idlibro":118,
      "titulo":"7 ESQUELETOS DECAPITADOS",
      "isbn":"9786077351047",
      "genero":"Ficción/Suspenso/Terror",
      "editorial":"OCEANO EL LADO OSCURO",
      "edicion":"#01",
      "proveedor":"GONVILL",
      "tipopasta":"RUSTICO",
      "autor":"ANTONIO MALPICA",
      "estado":"Bueno",
      "numpaginas":316,
      "fechaadq":"2013-03-07",
      "cantidadprest":"12"
   },
   {
      "idlibro":119,
      "titulo":"AFTER",
      "isbn":"9786070724268",
      "genero":"Romance/Novela",
      "editorial":"Planeta Mexico",
      "edicion":"#05",
      "proveedor":"LIBRERIAS GANDHI",
      "tipopasta":"BOLSILLO/TAPA BLANDA",
      "autor":"ANNA TODD",
      "estado":"Nuevo",
      "numpaginas":576,
      "fechaadq":"2014-08-04",
      "cantidadprest":"23"
   },
   {
      "idlibro":120,
      "titulo":"DIVINA COMEDIA",
      "isbn":"9788416734276",
      "genero":"Epopeya",
      "editorial":"GALAXIA GUTENBERG",
      "edicion":"#12",
      "proveedor":"LIBRERIAS GANDHI",
      "tipopasta":"TAPA DURA",
      "autor":"DANTE ALIGHIERI",
      "estado":"Bueno",
      "numpaginas":253,
      "fechaadq":"2016-09-12",
      "cantidadprest":"09"
   },
   {
      "idlibro":121,
      "titulo":"PEDRO PARAMO",
      "isbn":"987-123-65-4256-0",
      "genero":"NARRATIVO",
      "editorial":"TRILLAS",
      "edicion":"10 9 8 7 6 5 4 3 2 1",
      "proveedor":"TRILLAS",
      "tipopasta":"RUSTICA",
      "autor":"JUAN RULFO",
      "estado":"NO PRESTADO",
      "numpaginas":294,
      "fechaadq":"2022-02-22",
      "cantidadprest":"0"
   },
   {
      "idlibro":122,
      "titulo":"CIEN AÑOS DE SOLEDAD",
      "isbn":"987-123-65-4256-1",
      "genero":"NARRATIVO",
      "editorial":"AGUILAR",
      "edicion":"10 9 8 7 6 5",
      "proveedor":"AGULAR",
      "tipopasta":"RUSTICA",
      "autor":"GABRIEL GARCIA MARQUEZ",
      "estado":"PRESTADO",
      "numpaginas":455,
      "fechaadq":"2000-12-03",
      "cantidadprest":"5"
   },
   {
      "idlibro":123,
      "titulo":"EL AMOR EN LOS TIEMPOS DE COLERA",
      "isbn":"987-123-65-4256-2",
      "genero":"DRAMATICO",
      "editorial":"AGUILAR",
      "edicion":"10 9 8 7 6 5 4",
      "proveedor":"AGULAR",
      "tipopasta":"RUSTICA",
      "autor":"GABRIEL GARCIA MARQUEZ",
      "estado":"NO PRESTADO",
      "numpaginas":335,
      "fechaadq":"2002-04-03",
      "cantidadprest":"6"
   },
   {
      "idlibro":124,
      "titulo":"DON QUIJOTE DE LA MANCHA",
      "isbn":"987-123-65-4256-3",
      "genero":"NARRATIVO",
      "editorial":"MIRA-HADAS",
      "edicion":"10 9 8 7 6 5 4 3 2",
      "proveedor":"AGUILAR",
      "tipopasta":"RUSTICA",
      "autor":"MIGUEL DE CERVANTES",
      "estado":"NO PRESTADO",
      "numpaginas":226,
      "fechaadq":"2017-02-22",
      "cantidadprest":"3"
   },
   {
      "idlibro":125,
      "titulo":"EL CUERVO",
      "isbn":"987-123-65-4256-4",
      "genero":"LIRICO",
      "editorial":"PRE-TEXTOS",
      "edicion":"10 9 8 7 6 5 4 3 2 1",
      "proveedor":"AGUILAR",
      "tipopasta":"TELA",
      "autor":"EDGAR ALLAN POE",
      "estado":"PRESTADO",
      "numpaginas":449,
      "fechaadq":"2011-11-03",
      "cantidadprest":"8"
   },
   {
      "idlibro":126,
      "titulo":"FICCIONES",
      "isbn":"987-123-65-4256-5",
      "genero":"TEATRAL",
      "editorial":"TRILLAS",
      "edicion":"10 9 8 7 6 5",
      "proveedor":"AGUILAR",
      "tipopasta":"TELA",
      "autor":"JORGE LUIS BORGES",
      "estado":"NO PRESTADO",
      "numpaginas":336,
      "fechaadq":"2017-12-03",
      "cantidadprest":"6"
   },
   {
      "idlibro":127,
      "titulo":"RINCONETE Y CORTADILLO",
      "isbn":"987-123-65-4256-6",
      "genero":"NOVELA",
      "editorial":"ERRARA NATURA",
      "edicion":"10 9 8 7 6 5 4 3 2",
      "proveedor":"TRILLAS",
      "tipopasta":"RUSTICO",
      "autor":"MIGUEL DE CERVANTES",
      "estado":"NO PRESTADO",
      "numpaginas":449,
      "fechaadq":"2015-11-11",
      "cantidadprest":"6"
   },
   {
      "idlibro":128,
      "titulo":"CRONICA DE UNA MUERTE ANUNCIADA",
      "isbn":"987-123-65-4256-7",
      "genero":"NARRATIVO",
      "editorial":"TRILLAS",
      "edicion":"10 9 8 7 6 5 4 3 2 1",
      "proveedor":"TRILLAS",
      "tipopasta":"RUSTICA",
      "autor":"GABRIEL GARCIA MARQUEZ",
      "estado":"PRESTADO",
      "numpaginas":339,
      "fechaadq":"2019-11-01",
      "cantidadprest":"8"
   },
   {
      "idlibro":129,
      "titulo":"LA GALATEA",
      "isbn":"987-123-65-4256-8",
      "genero":"DRAMATICO",
      "editorial":"TRILLAS",
      "edicion":"10 9 8 7 6 5 4 3 2 1",
      "proveedor":"TRILLAS",
      "tipopasta":"TELA",
      "autor":"MIGUEL DE CERVANTES",
      "estado":"PRESTADO",
      "numpaginas":429,
      "fechaadq":"2022-01-08",
      "cantidadprest":"4"
   },
   {
      "idlibro":130,
      "titulo":"LA METAMORFOSIS",
      "isbn":"987-123-65-4256-9",
      "genero":"LIRICO",
      "editorial":"PRE-TEXTOS",
      "edicion":"10 9 8 7 6 5 4 3",
      "proveedor":"AGUILAR",
      "tipopasta":"HOLANDESA",
      "autor":"FRANZ KAFKA",
      "estado":"NO PRESTADO",
      "numpaginas":330,
      "fechaadq":"2017-01-22",
      "cantidadprest":"8"
   },
   {
      "idlibro":131,
      "titulo":"PESADILLAS",
      "isbn":"132102",
      "genero":"TERROR",
      "editorial":"PANINI",
      "edicion":"1ERA",
      "proveedor":"HISTORIA",
      "tipopasta":"TAPA DURA",
      "autor":"JOHAN",
      "estado":"PRESTADO",
      "numpaginas":280,
      "fechaadq":"2005-12-22",
      "cantidadprest":"50"
   },
   {
      "idlibro":132,
      "titulo":"AJEDREZ",
      "isbn":"132103",
      "genero":"ACADEMICO",
      "editorial":"NORMA",
      "edicion":"1ERA",
      "proveedor":"NORMA",
      "tipopasta":"TAPA DURA",
      "autor":"JASMINE",
      "estado":"PRESTADO",
      "numpaginas":200,
      "fechaadq":"2005-12-22",
      "cantidadprest":"20"
   },
   {
      "idlibro":133,
      "titulo":"THE BEGINNING AFTER THE END",
      "isbn":"132104",
      "genero":"FANTASIA",
      "editorial":"PANINI",
      "edicion":"2DA",
      "proveedor":"PANINI",
      "tipopasta":"TAPA BLANDA",
      "autor":"JOHAN",
      "estado":"PRESTADO",
      "numpaginas":280,
      "fechaadq":"2005-12-29",
      "cantidadprest":"105"
   },
   {
      "idlibro":134,
      "titulo":"TRABALENGUAS",
      "isbn":"132105",
      "genero":"ACADEMICO",
      "editorial":"NORMA",
      "edicion":"2DA",
      "proveedor":"NORMA",
      "tipopasta":"TAPA DURA",
      "autor":"ARTHUR",
      "estado":"PRESTADO",
      "numpaginas":250,
      "fechaadq":"2006-10-22",
      "cantidadprest":"210"
   },
   {
      "idlibro":135,
      "titulo":"HACKEAR",
      "isbn":"132106",
      "genero":"EDUCATIVO",
      "editorial":"SEVEN SEAS",
      "edicion":"5TA",
      "proveedor":"SEVEN SEAS",
      "tipopasta":"TAPA BLANDA",
      "autor":"JOAN AGUILAR",
      "estado":"PRESTADO",
      "numpaginas":400,
      "fechaadq":"2015-02-12",
      "cantidadprest":"120"
   },
   {
      "idlibro":136,
      "titulo":"PROGRAMACION",
      "isbn":"132107",
      "genero":"ACADEMICO",
      "editorial":"SEVEN SEAS",
      "edicion":"6TA",
      "proveedor":"SEVEN SEAS",
      "tipopasta":"TAPA DURA",
      "autor":"JOSE MARTÍNEZ",
      "estado":"PRESTADO",
      "numpaginas":200,
      "fechaadq":"2017-05-22",
      "cantidadprest":"150"
   },
   {
      "idlibro":137,
      "titulo":"THE CLASSROOM OF ELITE",
      "isbn":"132108",
      "genero":"FANTASIA",
      "editorial":"SEVEN SEAS",
      "edicion":"7MA",
      "proveedor":"SEVEN SEAS",
      "tipopasta":"TAPA BLANDA",
      "autor":"ARTURO JUAREZ",
      "estado":"PRESTADO",
      "numpaginas":199,
      "fechaadq":"2006-10-22",
      "cantidadprest":"50"
   },
   {
      "idlibro":138,
      "titulo":"ONE PIECE",
      "isbn":"132109",
      "genero":"FANTASIA",
      "editorial":"PANINI",
      "edicion":"8VA",
      "proveedor":"PANINI",
      "tipopasta":"TAPA DURA",
      "autor":"ECHIIRO ODA",
      "estado":"PRESTADO",
      "numpaginas":40,
      "fechaadq":"2007-02-25",
      "cantidadprest":"100"
   },
   {
      "idlibro":139,
      "titulo":"ALEMAN III",
      "isbn":"132110",
      "genero":"ACADEMICO",
      "editorial":"NORMA",
      "edicion":"9NA",
      "proveedor":"NORMA",
      "tipopasta":"TAPA DURA",
      "autor":"ITZEL FELIZ",
      "estado":"PRESTADO",
      "numpaginas":320,
      "fechaadq":"2011-11-02",
      "cantidadprest":"54"
   },
   {
      "idlibro":140,
      "titulo":"JAPONES",
      "isbn":"132111",
      "genero":"ACADEMICO",
      "editorial":"NORMA",
      "edicion":"10MA",
      "proveedor":"NORMA",
      "tipopasta":"TAPA DURA",
      "autor":"SYOUGO KINUGASA",
      "estado":"PRESTADO",
      "numpaginas":306,
      "fechaadq":"2017-05-01",
      "cantidadprest":"70"
   }
]